LICENSE
pydrinker_gcp/__init__.py
pydrinker_gcp/base.py
pydrinker_gcp/message_translators.py
pydrinker_gcp/providers.py
pydrinker_gcp/routes.py
pydrinker_gcp-1.1.2.dist-info/LICENSE
pydrinker_gcp-1.1.2.dist-info/WHEEL
pydrinker_gcp-1.1.2.dist-info/METADATA
pydrinker_gcp-1.1.2.dist-info/RECORD
